server/__init__.py
server/add_user.py
server/config_window.py
server/core.py
server/database.py
server/main_window.py
server/remove_user.py
server/stat_window.py
PyQt_server_client-0.0.1.dist-info/METADATA
PyQt_server_client-0.0.1.dist-info/WHEEL
PyQt_server_client-0.0.1.dist-info/top_level.txt
PyQt_server_client-0.0.1.dist-info/RECORD
