Metadata-Version: 2.1
Name: PyQt-server-client
Version: 0.0.1
Summary: Server_Client
Home-page: UNKNOWN
Author: Pavel Nedoshivin
Author-email: pnedoshivin@gmail.com
License: UNKNOWN
Platform: UNKNOWN
Requires-Dist: PyQt5
Requires-Dist: sqlalchemy
Requires-Dist: pycryptodome
Requires-Dist: pycryptodomex
